ca_certificates/__init__.py
wandb_widget-0.0.0.dist-info/METADATA
wandb_widget-0.0.0.dist-info/WHEEL
wandb_widget-0.0.0.dist-info/top_level.txt
wandb_widget-0.0.0.dist-info/RECORD
