Metadata-Version: 2.4
Name: wandb-widget
Version: 0.0.0
Summary: Dummy wandb-widget package for PyPI
Author-email: Your Name <you@example.com>
Requires-Python: >=3.7
